cozer.py
cozer-0.4.dist-info/LICENSE
cozer-0.4.dist-info/METADATA
cozer-0.4.dist-info/WHEEL
cozer-0.4.dist-info/entry_points.txt
cozer-0.4.dist-info/top_level.txt
cozer-0.4.dist-info/RECORD
