Metadata-Version: 2.1
Name: cozer
Version: 0.4
Summary: Um pequeno script para ensinar sobre como invocar comandos no terminal
Home-page: https://github.com/edusantana/cozer
Author: Eduardo de Santana Medeiros Alexandre
Author-email: eduardo.ufpb@gmail.com
License: UNKNOWN
Platform: UNKNOWN
Classifier: Programming Language :: Python :: 3
Classifier: License :: OSI Approved :: MIT License
Classifier: Operating System :: OS Independent
Requires-Dist: Click
Requires-Dist: click-didyoumean
